["```\n    kubectl create -f guestbook-all-in-one.yaml\n    ```", "```\n    kubectl get svc \n    ```", "```\n    kubectl edit service frontend\n    ```", "```\n    kubectl get svc -w\n    ```", "```\nkubectl scale deployment/frontend --replicas=6\n```", "```\nkubectl get pods\n```", "```\nkubectl get pods -o wide\n```", "```\n    kubectl scale deployment/frontend --replicas=1\n    ```", "```\n    1\u00a0\u00a0apiVersion: autoscaling/v2beta1\n    2\u00a0\u00a0kind: HorizontalPodAutoscaler\n    3\u00a0\u00a0metadata:\n    4\u00a0\u00a0\u00a0\u00a0name: frontend-scaler\n    5\u00a0\u00a0spec:\n    6\u00a0\u00a0\u00a0\u00a0scaleTargetRef:\n    7\u00a0\u00a0\u00a0\u00a0\u00a0\u00a0apiVersion: extensions/v1beta1\n    8\u00a0\u00a0\u00a0\u00a0\u00a0\u00a0kind: Deployment\n    9\u00a0\u00a0\u00a0\u00a0\u00a0\u00a0name: frontend\n    10\u00a0\u00a0\u00a0minReplicas: 1\n    11\u00a0\u00a0\u00a0maxReplicas: 10\n    12\u00a0\u00a0\u00a0metrics:\n    13\u00a0\u00a0\u00a0- type: Resource\n    14\u00a0\u00a0\u00a0\u00a0\u00a0resource:\n    15\u00a0\u00a0\u00a0\u00a0\u00a0\u00a0\u00a0name: cpu\n    16\u00a0\u00a0\u00a0\u00a0\u00a0\u00a0\u00a0targetAverageUtilization: 25\n    ```", "```\n    kubectl create -f hpa.yaml\n    ```", "```\n    kubectl get hpa\n    ```", "```\n    kubectl get pods -w\n    ```", "```\n    export GOPATH=~/go\n    export PATH=$GOPATH/bin:$PATH\n    go get -u github.com/rakyll/hey\n    hey -z 20m http://<external-ip>\n    ```", "```\n    kubectl describe hpa\n    ```", "```\n    kubectl get hpa -w\n    ```", "```\n    kubectl delete -f hpa.yaml\n    kubectl delete -f guestbook-all-in-one.yaml\n    ```", "```\nkubectl create -f guestbook-all-in-one.yaml\n```", "```\nkubectl scale deployment redis-slave --replicas 5\n```", "```\nkubectl get pods\n```", "```\naz aks nodepool update --enable-cluster-autoscaler \\\n\u00a0\u00a0-g rg-handsonaks --cluster-name handsonaks \\\n\u00a0\u00a0--name agentpool --min-count 1 --max-count 3\n```", "```\nkubectl get nodes -w\n```", "```\nkubectl get pods\n```", "```\nkubectl delete -f guestbook-all-in-one.yaml\naz aks nodepool update --disable-cluster-autoscaler \\\n\u00a0\u00a0-g rg-handsonaks --cluster-name handsonaks --name agentpool\naz aks nodepool scale --node-count 2 -g rg-handsonaks \\\n\u00a0\u00a0--cluster-name handsonaks --name agentpool\n```", "```\n    kubectl create -f guestbook-all-in-one.yaml\n    ```", "```\n    code guestbook-all-in-one.yaml\n    ```", "```\n    kubectl apply -f guestbook-all-in-one.yaml\n    ```", "```\n    kubectl get svc\n    ```", "```\n    image: gcr.io/google-samples/gb-frontend:v3\n    ```", "```\n    code guestbook-all-in-one.yaml\n    ```", "```\n    kubectl apply -f guestbook-all-in-one.yaml && kubectl get pods -w\n    ```", "```\n    kubectl get replicaset\n    ```", "```\n    kubectl rollout history deployment frontend\n    ```", "```\n    kubectl rollout undo deployment frontend\n    ```", "```\n    kubectl get replicaset\n    ```", "```\n    kubectl delete -f guestbook-all-in-one.yaml\n    ```", "```\n    kubectl create -f guestbook-all-in-one.yaml\n    ```", "```\n    kubectl edit service frontend\n    ```", "```\n    kubectl get svc -w\n    ```", "```\n    code frontend-image-patch.yaml\n    ```", "```\n    spec:\n    \u00a0\u00a0template:\n    \u00a0\u00a0\u00a0\u00a0spec:\n    \u00a0\u00a0\u00a0\u00a0\u00a0\u00a0containers:\n    \u00a0\u00a0\u00a0\u00a0\u00a0\u00a0- name: php-redis\n    \u00a0\u00a0\u00a0\u00a0\u00a0\u00a0\u00a0\u00a0image: gcr.io/google-samples/gb-frontend:v3\n    ```", "```\n    kubectl patch deployment frontend --patch \"$(cat frontend-image-patch.yaml)\"\n    ```", "```\n    kubectl describe deployment frontend\n    ```", "```\n    kubectl patch deployment frontend --patch='{\"spec\":{\"template\":{\"spec\":{\"containers\":[{\"name\":\"php-redis\",\"image\":\"gcr.io/google-samples/gb-frontend:v4\"}]}}}}'\n    ```", "```\n    kubectl describe deployment frontend\n    ```", "```\nkubectl delete -f guestbook-all-in-one.yaml\n```", "```\n    helm install wp stable/wordpress\n    ```", "```\n    kubectl describe statefulset wp-mariadb | grep Image\n    ```", "```\n    kubectl get secret wp-mariadb -o yaml\n    ```", "```\n    echo \"<password>\" | base64 -d\n    ```", "```\n    helm upgrade wp stable/wordpress --set mariadb.image.tag=10.3.21-debian-10-r1,mariadb.rootUser.password=<decoded password>,mariadb.db.password=<decoded db password> && kubectl get pods -w\n    ```", "```\n    kubectl describe pod wp-mariadb-0 | grep Image\n    ```", "```\n    helm delete wp\n    kubectl delete pvc --all\n    kubectl delete pv --all\n    ```"]