["```js\nvar express = require(\"express\"),\n    app = express();\n\napp.get(\"/\", function (req, res) {\n    var output = \"\";\n    output += '<form action=\"/test\">';\n    output += '<input name=\"name\" placeholder=\"enter a name\">';\n    output += '</form>';\n\n    res.send(output);\n});\n\napp.get(\"/test\", function (req, res) {\n    res.send(\"Hello, \" + req.query.name);\n});\n\napp.listen(3000);\n```", "```js\nvar sql = \"SELECT * FROM users WHERE name = '\" + username + \"'\";\n```", "```js\nSELECT * FROM users WHERE name = 'Dominic'\n```", "```js\nSELECT * FROM users WHERE name = '' OR 1=1\n```", "```js\nSELECT * FROM users WHERE name = ''; DROP TABLE users;\n```", "```js\n<h2>User: <%= username %></h2>\n```", "```js\n<h2>User: <script>alert('xss');</script></h2>\n```", "```js\n<img height=<%= height %> src=\"img/...\">\n```", "```js\n<img height=100 onload=\"javascript:alert('XSS');\" src=\"img/...\">\n```", "```js\n<a href=\"<%= url %>\">Home Page</a>\n```", "```js\n<a href=\"javascript:alert('XSS');\">Home Page</a>\n```", "```js\n<a href=\"/article?page=<%= nextPage %>\">Next</a>\n```", "```js\n<script>\nvar clientData = <%= JSON.stringify(serverData); %>;\n</script>\n```", "```js\n<script>\nvar clientData = {\"username\":\"</script><script>alert('XSS');</script>\"};\n</script>\n```", "```js\n<script id=\"serverData\" type=\"application/json\">\n<%= html_escape(JSON.stringify(data)) %>\n</script>\n\n<script>\nvar dataElement = document.getElementById(\"serverData\");\nvar dataText = dataElement.textContent || dataElement.innerText; // unescapes the content of the script\nvar data = JSON.parse(dataText);\n </script>\n```", "```js\nContent-Security-Policy: script-src 'self'\n```", "```js\nContent-Security-Policy: script-src 'self'; frame-src 'none'; object-src 'none'\n```", "```js\nContent-Security-Policy: default-src 'self'\n```", "```js\napp.use(helmet.csp.policy({\n    defaultPolicy: {\n        \"script-src\": [ \"'self'\" ],\n        \"img-src\": [ \"'self'\", \"http://example.com/\" ]\n    }\n}));\n```", "```js\nContent-Security-Policy: script-src 'self'; img-src 'self' http://example.com/\n```", "```js\nContent-Security-Policy: default-src 'self'; ...; report-uri /my_csp_report_parser;\n```", "```js\n{\n  \"csp-report\": {\n    \"document-uri\": \"http://example.org/page.html\",\n    \"referrer\": \"http://evil.example.com/\",\n    \"blocked-uri\": \"http://evil.example.com/evil.js\",\n    \"violated-directive\": \"script-src 'self' https://apis.google.com\",\n    \"original-policy\": \"script-src 'self' https://apis.google.com; report-uri http://example.org/my_amazing_csp_report_parser\"\n  }\n}\n```", "```js\nContent-Security-Policy-Report-Only: default-src 'self'; ...; report-uri /my_csp_report_parser;\n```", "```js\nexpress.use(helmet.csp.policy({\n    reportOnly: true,\n    defaultPolicy: {\n        \"script-src\": [ \"'self'\" ],\n        \"img-src\": [ \"'self'\", \"http://example.com/\" ]\n    }\n}));\n```", "```js\nStrict-Transport-Security: max-age=15768000\n```", "```js\napp.use(helmet.hsts());\n```", "```js\napp.use(helmet.hsts(1234567, true));\n```", "```js\nStrict-Transport-Security: max-age=1234567; includeSubdomains\n```", "```js\nX-Frame-Options: DENY\n```", "```js\napp.use(helmet.xframe());\n```", "```js\nhelmet.xframe('sameorigin');\n```", "```js\nhelmet.xframe('allow-from', 'http://example.com');\n```", "```js\nX-XSS-Protection: 1; mode=block\n```", "```js\napp.use(helmet.iexss());\n```", "```js\nX-Content-Type-Options: nosniff\n```", "```js\napp.use(helmet.contentTypeOptions());\n```", "```js\napp.use(helmet.cacheControl());\n```"]